aiogram_sqlite_storage/__init__.py
aiogram_sqlite_storage/sqlitestore.py
aiogram_sqlite_storage-1.0.0.dist-info/METADATA
aiogram_sqlite_storage-1.0.0.dist-info/WHEEL
aiogram_sqlite_storage-1.0.0.dist-info/licenses/LICENSE
aiogram_sqlite_storage-1.0.0.dist-info/RECORD
