Metadata-Version: 2.1
Name: aiogram_sqlite_storage
Version: 1.0.0
Summary: A FSM Storage for aiogram 3.0+, based on SQLite.
Project-URL: Homepage, https://github.com/sashaferrum/aiogram_sqlite_storage
Author-email: Aleksandr Zheleznov <sasha.ferrum@gmail.com>
License-File: LICENSE
Keywords: aiogram,asyncio,fsm,json,pickle,storage,telegram
Classifier: Operating System :: OS Independent
Classifier: Programming Language :: Python :: 3
Requires-Python: >=3.8
Requires-Dist: aiogram>=3.0.0
